{
	"name": "Restar",
	"description": "Charts & Graphs for Web Applications built on React components",
	"color": {
		"premium": "#F7FF00",
		"secondary": "#676A0D"
	},
	"iconId": "restar",
	"version": "0.1.1",
	"navlink": [{
			"label": "Home",
			"link": "./"
		},
		{
			"label": "Demo",
			"link": "./demo"
		},
		{
			"label": "Docs",
			"link": "./docs"
		},
		{
			"label": "Github",
			"link": "./Github"
		}
	],
	"contents": [{
		"title": "Installation",
		"type": "",
		"text": "Rechart source files via npm. We take care of injecting the CSS needed. \n\n ```shell \n $ npm install rechart or use a CDN. \n```"
	},
	{
		"title": "Usage",
		"type": "",
		"text": "Rechart source files via npm. We take care of injecting the CSS needed. \n\n ```shell \n $ npm install rechart or use a CDN. \n``` \n Rechart source files via npm. We take care of injecting the CSS needed. \n\n ```shell \n $ npm install rechart or use a CDN. \n``` \n Rechart source files via npm. We take care of injecting the CSS needed. \n\n ```shell \n $ npm install rechart or use a CDN. \n``` \n Rechart source files via npm. We take care of injecting the CSS needed. \n\n ```shell \n $ npm install rechart or use a CDN. \n``` \n Rechart source files via npm. We take care of injecting the CSS needed. \n\n ```shell \n $ npm install rechart or use a CDN. \n```"
	},
	{
		"title": "Themes",
		"type": "",
		"text": "Rechart source files via npm. We take care of injecting the CSS needed. $ npm install rechart or use a CDN."
	}
]
}